pytorch_lattice/__init__.py
pytorch_lattice/classifier.py
pytorch_lattice/constrained_module.py
pytorch_lattice/datasets.py
pytorch_lattice/enums.py
pytorch_lattice/feature_config.py
pytorch_lattice/layers/__init__.py
pytorch_lattice/layers/categorical_calibrator.py
pytorch_lattice/layers/lattice.py
pytorch_lattice/layers/linear.py
pytorch_lattice/layers/numerical_calibrator.py
pytorch_lattice/layers/rtl.py
pytorch_lattice/model_configs.py
pytorch_lattice/models/__init__.py
pytorch_lattice/models/calibrated_lattice.py
pytorch_lattice/models/calibrated_linear.py
pytorch_lattice/models/features.py
pytorch_lattice/plots.py
pytorch_lattice/utils/__init__.py
pytorch_lattice/utils/data.py
pytorch_lattice/utils/models.py
pytorch_lattice-0.2.0.dist-info/LICENSE
pytorch_lattice-0.2.0.dist-info/METADATA
pytorch_lattice-0.2.0.dist-info/WHEEL
pytorch_lattice-0.2.0.dist-info/RECORD
