Metadata-Version: 2.1
Name: pytorch-lattice
Version: 0.2.0
Summary: A PyTorch Implementation Of Lattice Modeling Techniques
Home-page: https://github.com/willbakst/pytorch-lattice
License: MIT
Author: William Bakst
Author-email: william@mirascope.io
Requires-Python: >=3.9,<=3.12
Classifier: License :: OSI Approved :: MIT License
Classifier: Programming Language :: Python :: 3
Classifier: Programming Language :: Python :: 3.9
Classifier: Programming Language :: Python :: 3.10
Classifier: Programming Language :: Python :: 3.11
Classifier: Programming Language :: Python :: 3.12
Requires-Dist: matplotlib (>=3.7.1,<4.0.0)
Requires-Dist: numpy (>=1.23.5,<2.0.0)
Requires-Dist: pandas (>=2.0.2,<3.0.0)
Requires-Dist: pydantic (>=2.0.2,<3.0.0)
Requires-Dist: torch (>=2.0.0,!=2.0.1,!=2.1.0)
Requires-Dist: tqdm (>=4.65.0,<5.0.0)
Project-URL: Repository, https://github.com/willbakst/pytorch-lattice
